understar/.version
understar/__init__.py
understar/understar.py
understar/system/__init__.py
understar/system/app/__init__.py
understar/system/app/config/__init__.py
understar/system/app/config/apt/__init__.py
understar/system/app/config/apt/install.py
understar/system/app/config/apt/uninstall.py
understar/system/app/config/update/__init__.py
understar/system/app/config/update/update.py
understar/system/app/maintenance/__init__.py
understar/system/lib/__init__.py
understar/system/lib/app.py
understar/system/lib/com.py
understar/system/lib/event.py
understar/system/lib/save.py
understar/system/lib/store.py
understar/system/lib/types.py
understar/system/lib/utils.py
understar-2.72.dist-info/LICENSE
understar-2.72.dist-info/METADATA
understar-2.72.dist-info/WHEEL
understar-2.72.dist-info/top_level.txt
understar-2.72.dist-info/RECORD
