Metadata-Version: 2.1
Name: understar
Version: 2.72
Summary: A discord bot framework
Home-page: https://github.com/GalTechDev/UnderStar-OS
Download-URL: https://github.com/GalTechDev/UnderStar-OS/tarball/master
Author: GalTech
Author-email: poussigalitv@gmail.com
License: MIT
Keywords: discord,bot,discord.py,understar,os,framework
Classifier: Programming Language :: Python :: 3
Classifier: License :: OSI Approved :: MIT License
Classifier: Operating System :: OS Independent
Requires-Python: >=3.10
License-File: LICENSE
Requires-Dist: discord.py >=2.3.1
Requires-Dist: gitpython
Requires-Dist: lxml ==4.9.3
Requires-Dist: requests-html ==0.10.0
